Metadata-Version: 2.1
Name: seedr
Version: 1.2.1
Summary: Unofficial API wrapper for seedr.cc .
Home-page: https://github.com/AnjanaMadu/SeedrAPI
Author: Anjana Madu
Author-email: hello@anjanamadu.net
License: GPL 3.0
Project-URL: Documentation, https://github.com/AnjanaMadu/SeedrAPI/wiki
Project-URL: Source, https://github.com/AnjanaMadu/SeedrAPI
Keywords: seedr,seedr.cc,seedr-api
Classifier: Development Status :: 5 - Production/Stable
Classifier: Intended Audience :: Developers
Classifier: Natural Language :: English
Classifier: Operating System :: OS Independent
Classifier: Programming Language :: Python
Classifier: Programming Language :: Python :: 3
Classifier: Programming Language :: Python :: 3.7
Classifier: Programming Language :: Python :: 3.8
Classifier: Programming Language :: Python :: 3.9
Classifier: Programming Language :: Python :: 3.10
Classifier: Programming Language :: Python :: 3.11
Classifier: Programming Language :: Python :: 3 :: Only
Classifier: Topic :: Software Development :: Libraries
Requires-Python: >=3.7, <4
License-File: LICENSE
